ani_cli_arabic-1.8.1.dist-info/licenses/LICENSE
src/__init__.py
src/__main__.py
src/api.py
src/app.py
src/cli.py
src/config.py
src/deps.py
src/discord_rpc.py
src/favorites.py
src/history.py
src/models.py
src/monitoring.py
src/player.py
src/settings.py
src/ui.py
src/updater.py
src/utils.py
src/version.py
ani_cli_arabic-1.8.1.dist-info/METADATA
ani_cli_arabic-1.8.1.dist-info/WHEEL
ani_cli_arabic-1.8.1.dist-info/entry_points.txt
ani_cli_arabic-1.8.1.dist-info/top_level.txt
ani_cli_arabic-1.8.1.dist-info/RECORD
