Metadata-Version: 2.4
Name: ani-cli-arabic
Version: 1.8.1
Summary: Terminal-based anime streaming with Arabic subtitles
Author: np4abdou1
Maintainer: np4abdou1
License-Expression: GPL-3.0
Project-URL: Homepage, https://github.com/np4abdou1/ani-cli-arabic
Project-URL: Repository, https://github.com/np4abdou1/ani-cli-arabic
Project-URL: Issues, https://github.com/np4abdou1/ani-cli-arabic/issues
Project-URL: Changelog, https://github.com/np4abdou1/ani-cli-arabic/releases
Keywords: anime,streaming,cli,arabic,subtitles,terminal
Classifier: Development Status :: 4 - Beta
Classifier: Intended Audience :: End Users/Desktop
Classifier: Operating System :: OS Independent
Classifier: Programming Language :: Python :: 3
Classifier: Programming Language :: Python :: 3.8
Classifier: Programming Language :: Python :: 3.9
Classifier: Programming Language :: Python :: 3.10
Classifier: Programming Language :: Python :: 3.11
Classifier: Programming Language :: Python :: 3.12
Classifier: Topic :: Multimedia :: Video
Classifier: Environment :: Console
Requires-Python: >=3.8
License-File: LICENSE
Requires-Dist: rich>=13.0.0
Requires-Dist: requests>=2.31.0
Requires-Dist: pypresence>=4.5.0
Requires-Dist: yt-dlp
Requires-Dist: Pillow>=10.0.0
Requires-Dist: numpy>=1.24.0
Dynamic: license-file
